hichip_peaks/__init__.py
hichip_peaks/bedgraph.py
hichip_peaks/diffpeaks.py
hichip_peaks/helpers.py
hichip_peaks/interaction_to_sparse.py
hichip_peaks/main.py
hichip_peaks/quality_report.py
hichip_peaks/site_matrix_class.py
hichip_peaks/sparse_to_peaks.py
hichip_peaks-0.1.2.dist-info/LICENSE
hichip_peaks-0.1.2.dist-info/METADATA
hichip_peaks-0.1.2.dist-info/WHEEL
hichip_peaks-0.1.2.dist-info/entry_points.txt
hichip_peaks-0.1.2.dist-info/top_level.txt
hichip_peaks-0.1.2.dist-info/RECORD
