Metadata-Version: 2.1
Name: hichip-peaks
Version: 0.1.2
Summary: A tool to find peaks from hichip data
Home-page: https://github.com/ChenfuShi/HiChIP_peaks
Author: Chenfu Shi
Author-email: chenfu.shi@postgrad.manchester.ac.uk
License: BSD
Platform: UNKNOWN
Classifier: Development Status :: 3 - Alpha
Classifier: Environment :: Console
Classifier: Intended Audience :: Developers
Classifier: Intended Audience :: Science/Research
Classifier: Natural Language :: English
Classifier: Operating System :: POSIX :: Linux
Classifier: Programming Language :: Python :: 3
Classifier: Programming Language :: Python :: 3.6
Classifier: Programming Language :: Python :: 3.7
Classifier: Topic :: Scientific/Engineering :: Bio-Informatics
Classifier: License :: OSI Approved :: BSD License
Requires-Python: >=3.6
Requires-Dist: scipy
Requires-Dist: numpy
Requires-Dist: statsmodels
Requires-Dist: matplotlib
